my_crypto_lib/__init__.py
my_crypto_lib/info.py
my_crypto_lib/ciphers/__init__.py
my_crypto_lib/ciphers/aes.py
my_crypto_lib/ciphers/all.py
my_crypto_lib/ciphers/caesar.py
my_crypto_lib/ciphers/deffie.py
my_crypto_lib/ciphers/des.py
my_crypto_lib/ciphers/dss.py
my_crypto_lib/ciphers/hill.py
my_crypto_lib/ciphers/ids.py
my_crypto_lib/ciphers/md5.py
my_crypto_lib/ciphers/playfair.py
my_crypto_lib/ciphers/railfence.py
my_crypto_lib/ciphers/rsa.py
my_crypto_lib/ciphers/sha_512.py
my_crypto_lib/ciphers/vigenere.py
my_crypto_lib-1.0.0.dist-info/LICENSE
my_crypto_lib-1.0.0.dist-info/METADATA
my_crypto_lib-1.0.0.dist-info/WHEEL
my_crypto_lib-1.0.0.dist-info/top_level.txt
my_crypto_lib-1.0.0.dist-info/RECORD
